setup.py
textwrite.egg-info/PKG-INFO
textwrite.egg-info/SOURCES.txt
textwrite.egg-info/dependency_links.txt
textwrite.egg-info/top_level.txt
write/__init__.py