Metadata-Version: 2.4
Name: textwrite
Version: 0.1
Summary: A simple typewriter-style text output function
Author: Charles Q
Requires-Python: >=3.6
Dynamic: author
Dynamic: requires-python
Dynamic: summary
